cloudteamisgreat/MANIFEST.in
cloudteamisgreat/__init__.py
cloudteamisgreat/main.py
cloudteamisgreat/setup.py
cloudteamisgreat/version.py
cloudteamisgreat/__pycache__/__init__.cpython-310.pyc
cloudteamisgreat/__pycache__/main.cpython-310.pyc
cloudteamisgreat/__pycache__/version.cpython-310.pyc
cloudteamisgreat/yaml/logging.yaml
cloudteamisgreat-0.0.2.dist-info/LICENSE
cloudteamisgreat-0.0.2.dist-info/METADATA
cloudteamisgreat-0.0.2.dist-info/WHEEL
cloudteamisgreat-0.0.2.dist-info/entry_points.txt
cloudteamisgreat-0.0.2.dist-info/top_level.txt
cloudteamisgreat-0.0.2.dist-info/RECORD
