Metadata-Version: 2.1
Name: cloudteamisgreat
Version: 0.0.2
Summary: cloudteamisgreat
Author-email: WeiYu <wychen@narlabs.org.tw>
License: apache2
Keywords: ckan
Classifier: Topic :: Database :: Front-Ends
Classifier: Programming Language :: Python :: 3
Requires-Python: >=3.6
License-File: LICENSE
Requires-Dist: requests
Requires-Dist: configparser
